YN_Exchange/AsyncExchange.py
YN_Exchange/Exchange.py
YN_Exchange/__init__.py
ynexchangepy-6.0.2.dist-info/METADATA
ynexchangepy-6.0.2.dist-info/WHEEL
ynexchangepy-6.0.2.dist-info/top_level.txt
ynexchangepy-6.0.2.dist-info/RECORD
