Metadata-Version: 2.4
Name: YnExchangePY
Version: 6.0.2
Summary: OpenSource Crypto Library
Author: Yasha Najafi(YN)
Author-email: najafiyasha@gmail.com
License: MIT
Keywords: python,crypto,prices,crypto calculations,api,calculations,metal
Requires-Dist: bs4
Requires-Dist: plotly
Requires-Dist: matplotlib
Requires-Dist: mplfinance
Requires-Dist: ccxt
Requires-Dist: ccxt
Requires-Dist: pandas
Requires-Dist: urllib3
Requires-Dist: asyncio
Requires-Dist: aiohttp
Dynamic: author
Dynamic: author-email
Dynamic: description
Dynamic: description-content-type
Dynamic: keywords
Dynamic: license
Dynamic: requires-dist
Dynamic: summary
